pdf_hider/__init__.py
pdf_hider/main.py
pdf_hider-0.1.0.dist-info/METADATA
pdf_hider-0.1.0.dist-info/WHEEL
pdf_hider-0.1.0.dist-info/entry_points.txt
pdf_hider-0.1.0.dist-info/top_level.txt
pdf_hider-0.1.0.dist-info/RECORD
