Metadata-Version: 2.4
Name: pdf-hider
Version: 0.1.0
Summary: A tool to embed hidden, transparent text into PDF files.
Home-page: https://github.com/your-username/pdf-hidden-text-tool
Author: Youfa
Author-email: hi@youfa.me
Keywords: pdf hidden text transparency ai resume
Classifier: Programming Language :: Python :: 3
Classifier: License :: OSI Approved :: MIT License
Classifier: Operating System :: OS Independent
Classifier: Development Status :: 3 - Alpha
Classifier: Intended Audience :: Developers
Classifier: Topic :: Text Processing
Classifier: Topic :: Utilities
Requires-Python: >=3.6
Requires-Dist: PyPDF2==3.0.1
Requires-Dist: reportlab==4.0.0
Dynamic: author
Dynamic: author-email
Dynamic: classifier
Dynamic: description
Dynamic: description-content-type
Dynamic: home-page
Dynamic: keywords
Dynamic: requires-dist
Dynamic: requires-python
Dynamic: summary
